<?xml version="1.0"?><Settings> <Sounds> <Sound Value="1.0" Mute="false" /> <Music Value="1.0" Mute="false" /> </Sounds> <ShowIntro Value="1" /> <Config> <Avatar Name="avatar_hero" /> <Skeleton Player="Skeleton" /> <Location Name="dojo" /> <Armor Name="Body" /> <Helmet Name="Head" /> <Weapon Name="Fists" /> <TutorialWeapon Name="WEAPON_KNIVES" /> <TutorialBoss Name="ZONE_1|BOSS_LYNX|1" /> <LossReward Exp="2" Money="0" PrizeBase="25" /> <SellItems Value="0.1" /> <RewardsPrize> <Perfect Value="0.1" /> <FirstStrike Value="0.02" /> <ComboCount Value="0.01" /> <HeadShot Value="0.01" /> <Styles> <Turtle Value="0" /> <Hard Value="0.025" /> <Brutal Value="0.05" /> <Agressive Value="0.075" /> <Crazy Value="0.1" /> <Fantastic Value="0.125" /> </Styles> </RewardsPrize> <BlockDamage Value="0.2" /> <Critical> <CriticalDamage Value="2" /> <CriticalProbality Value="0.1" /> <CriticalPauseTime Value="60" /> <CriticalEffectTime Value="90" /> <CriticalAmplitudeX Value="5" /> <CriticalFrequencyX Value="1.1" /> <CriticalAmplitudeY Value="15" /> <CriticalFrequencyY Value="1" /> </Critical> </Config> <Language Value="assets/localizations/eng.xml" Number="0" /></Settings>